geostack/_version.py
geostack/gs_enums.py
geostack/__init__.py
geostack/definitions.py
geostack/.libs/libgomp-9400ba07.so.1.0.0
geostack/.libs/libGeostack-d26863cd.so
geostack/.libs/libOpenCL-869622d5.so.1.0.0
geostack/readers/tiffutils.py
geostack/readers/timeutils.py
geostack/readers/ftputils.py
geostack/readers/ncutils.py
geostack/readers/gribReader.py
geostack/readers/vectorReaders.py
geostack/readers/rasterReaders.py
geostack/readers/__init__.py
geostack/readers/test/test_grib_reader.py
geostack/readers/test/test_time_utils.py
geostack/readers/test/__init__.py
geostack/readers/test/test_vector_readers.py
geostack/readers/test/test_raster_readers.py
geostack/writers/netcdfWriter.py
geostack/writers/rasterWriters.py
geostack/writers/__init__.py
geostack/writers/vectorWriters.py
geostack/writers/test/__init__.py
geostack/writers/test/test_vector_writer.py
geostack/writers/test/test_raster_writer.py
geostack/dataset/__init__.py
geostack/dataset/supported_libs.py
geostack/dataset/dataset.py
geostack/raster/_cy_raster.cpython-310-x86_64-linux-gnu.so
geostack/raster/__init__.py
geostack/raster/_base.py
geostack/raster/_cy_raster.pxd
geostack/raster/raster.py
geostack/raster/test/test_raster_list.py
geostack/raster/test/test_numpy_interop.py
geostack/raster/test/__init__.py
geostack/raster/test/test_raster.py
geostack/raster/test/test_raster_pickle.py
geostack/raster/test/test_raster_random.py
geostack/solvers/_cy_particle.cpython-310-x86_64-linux-gnu.so
geostack/solvers/particle.py
geostack/solvers/_cy_network_flow.cpython-310-x86_64-linux-gnu.so
geostack/solvers/ode.py
geostack/solvers/_cy_level_set.cpython-310-x86_64-linux-gnu.so
geostack/solvers/__init__.py
geostack/solvers/multigrid.py
geostack/solvers/_cy_shallow_water.cpython-310-x86_64-linux-gnu.so
geostack/solvers/shallow_water.py
geostack/solvers/level_set.py
geostack/solvers/_cy_multigrid.cpython-310-x86_64-linux-gnu.so
geostack_py-0.4.8.dist-info/WHEEL
geostack_py-0.4.8.dist-info/METADATA
geostack_py-0.4.8.dist-info/top_level.txt
geostack_py-0.4.8.dist-info/RECORD
geostack_py-0.4.8.dist-info/LICENSE
